kinto_nexmo_verify/__init__.py
kinto_nexmo_verify/authentication.py
kinto_nexmo_verify/conf.py
kinto_nexmo_verify/views.py
kinto_nexmo_verify/tests/__init__.py
kinto_nexmo_verify/tests/test_authentication.py
kinto_nexmo_verify/tests/test_includeme.py
kinto_nexmo_verify/tests/test_views.py
kinto_nexmo_verify-1.0.0.dist-info/LICENSE
kinto_nexmo_verify-1.0.0.dist-info/METADATA
kinto_nexmo_verify-1.0.0.dist-info/WHEEL
kinto_nexmo_verify-1.0.0.dist-info/top_level.txt
kinto_nexmo_verify-1.0.0.dist-info/RECORD
