Metadata-Version: 2.1
Name: kinto-nexmo-verify
Version: 1.0.0
Summary: Nexmo Verify Passwordless support for Kinto
Home-page: https://github.com/Kinto/kinto-nexmo-verify
Author: Rémy Hubscher
Author-email: remy@chefclub.tv
License: Apache License (2.0)
Keywords: kinto nexmo sms voice authentication
Platform: UNKNOWN
Classifier: Programming Language :: Python
Classifier: Programming Language :: Python :: 3
Classifier: Programming Language :: Python :: 3.6
Classifier: Programming Language :: Python :: 3.7
Classifier: Programming Language :: Python :: 3.8
Classifier: Topic :: Internet :: WWW/HTTP
Classifier: Topic :: Internet :: WWW/HTTP :: WSGI :: Application
Classifier: License :: OSI Approved :: Apache Software License
Requires-Dist: kinto
Requires-Dist: nexmo
